pytest_harvest/__init__.py
pytest_harvest/_version.py
pytest_harvest/common.py
pytest_harvest/fixture_cache.py
pytest_harvest/newhooks.py
pytest_harvest/plugin.py
pytest_harvest/py.typed
pytest_harvest/results_bags.py
pytest_harvest/results_session.py
pytest_harvest/xdist_api.py
pytest_harvest-1.10.5.dist-info/LICENSE
pytest_harvest-1.10.5.dist-info/METADATA
pytest_harvest-1.10.5.dist-info/WHEEL
pytest_harvest-1.10.5.dist-info/entry_points.txt
pytest_harvest-1.10.5.dist-info/top_level.txt
pytest_harvest-1.10.5.dist-info/RECORD
